kiroker/__init__.py
kiroker/__main__.py
kiroker/main.py
kiroker-0.1.0.dist-info/LICENSE
kiroker-0.1.0.dist-info/WHEEL
kiroker-0.1.0.dist-info/METADATA
kiroker-0.1.0.dist-info/RECORD
