Metadata-Version: 2.1
Name: kiroker
Version: 0.1.0
Summary: A changelog generator.
License: MIT
Author: Ryosuke Imai
Author-email: imai@qunasys.com
Requires-Python: >=3.7,<4.0
Classifier: License :: OSI Approved :: MIT License
Classifier: Programming Language :: Python :: 3
Classifier: Programming Language :: Python :: 3.10
Classifier: Programming Language :: Python :: 3.7
Classifier: Programming Language :: Python :: 3.8
Classifier: Programming Language :: Python :: 3.9
Requires-Dist: PyYAML (>=6.0,<7.0)
